{
    "/Volumes/LaCie/2026/March - Red Sea Egypt/61 Ocean Lovers Egypt - Marsa Shouna/VID_20260326_111740_185.mp4": {
        "default": {
            "totalFrames": 4159,
            "trimEnd": 4159,
            "trimStart": 0,
            "updateTime": 0
        }
    },
    "/Volumes/LaCie/2026/March - Red Sea Egypt/61 Ocean Lovers Egypt - Marsa Shouna/media/797901007.578325_29331776208212.MP4": {
        "default": {
            "totalFrames": 12830,
            "trimEnd": 12830,
            "trimStart": 0,
            "updateTime": 0
        }
    },
    "/Volumes/LaCie/2026/March - Red Sea Egypt/61 Ocean Lovers Egypt - Marsa Shouna/media/797947460.183426_12221776254664.MP4": {
        "default": {
            "totalFrames": 4142,
            "trimEnd": 4142,
            "trimStart": 0,
            "updateTime": 0
        }
    },
    "/Volumes/LaCie/2026/March - Red Sea Egypt/61 Ocean Lovers Egypt - Marsa Shouna/media/798067959.714426_12211776375163.MP4": {
        "default": {
            "totalFrames": 5614,
            "trimEnd": 5614,
            "trimStart": 0,
            "updateTime": 0
        }
    },
    "/Volumes/LaCie/2026/March - Red Sea Egypt/61 Ocean Lovers Egypt - Marsa Shouna/media/798068274.040194_12691776375477.MP4": {
        "default": {
            "totalFrames": 623,
            "trimEnd": 623,
            "trimStart": 0,
            "updateTime": 0
        }
    },
    "/Volumes/LaCie/2026/March - Red Sea Egypt/61 Ocean Lovers Egypt - Marsa Shouna/media/798068443.932685_13151776375648.MP4": {
        "default": {
            "totalFrames": 3989,
            "trimEnd": 3989,
            "trimStart": 0,
            "updateTime": 0
        }
    },
    "/Volumes/LaCie/2026/March - Red Sea Egypt/61 Ocean Lovers Egypt - Marsa Shouna/media/798068975.652551_13651776376179.MP4": {
        "default": {
            "totalFrames": 2930,
            "trimEnd": 2930,
            "trimStart": 0,
            "updateTime": 0
        }
    },
    "/Volumes/LaCie/2026/March - Red Sea Egypt/61 Ocean Lovers Egypt - Marsa Shouna/media/798069321.319743_14111776376525.MP4": {
        "default": {
            "totalFrames": 1012,
            "trimEnd": 1012,
            "trimStart": 0,
            "updateTime": 0
        }
    },
    "/Volumes/LaCie/2026/March - Red Sea Egypt/61 Ocean Lovers Egypt - Marsa Shouna/media/798069392.74461_14571776376597.MP4": {
        "default": {
            "totalFrames": 4444,
            "trimEnd": 4444,
            "trimStart": 0,
            "updateTime": 0
        }
    },
    "/Volumes/LaCie/2026/March - Red Sea Egypt/61 Ocean Lovers Egypt - Marsa Shouna/media/798069625.724725_15031776376830.MP4": {
        "default": {
            "totalFrames": 6614,
            "trimEnd": 6614,
            "trimStart": 0,
            "updateTime": 0
        }
    },
    "/Volumes/LaCie/2026/March - Red Sea Egypt/61 Ocean Lovers Egypt - Marsa Shouna/media/798070014.472407_15491776377219.MP4": {
        "default": {
            "totalFrames": 1739,
            "trimEnd": 1739,
            "trimStart": 0,
            "updateTime": 0
        }
    },
    "/Volumes/LaCie/2026/March - Red Sea Egypt/61 Ocean Lovers Egypt - Marsa Shouna/media/798070138.366674_15951776377344.MP4": {
        "default": {
            "totalFrames": 2113,
            "trimEnd": 2113,
            "trimStart": 0,
            "updateTime": 0
        }
    },
    "/Volumes/LaCie/2026/March - Red Sea Egypt/61 Ocean Lovers Egypt - Marsa Shouna/media/798070255.874224_16411776377460.MP4": {
        "default": {
            "totalFrames": 4498,
            "trimEnd": 4498,
            "trimStart": 0,
            "updateTime": 0
        }
    },
    "/Volumes/LaCie/2026/March - Red Sea Egypt/61 Ocean Lovers Egypt - Marsa Shouna/media/798070499.358547_16871776377704.MP4": {
        "default": {
            "totalFrames": 5977,
            "trimEnd": 5977,
            "trimStart": 0,
            "updateTime": 0
        }
    },
    "/Volumes/LaCie/2026/March - Red Sea Egypt/61 Ocean Lovers Egypt - Marsa Shouna/media/798070814.502707_17331776378019.MP4": {
        "default": {
            "totalFrames": 2850,
            "trimEnd": 2850,
            "trimStart": 0,
            "updateTime": 0
        }
    },
    "/Volumes/LaCie/2026/March - Red Sea Egypt/61 Ocean Lovers Egypt - Marsa Shouna/media/IMG_1932 copy.jpg": {
        "default": {
            "totalFrames": 900,
            "trimEnd": 900,
            "trimStart": 0,
            "updateTime": 0
        }
    },
    "/Volumes/LaCie/2026/March - Red Sea Egypt/61 Ocean Lovers Egypt - Marsa Shouna/media/IMG_1933 copy.jpg": {
        "default": {
            "totalFrames": 900,
            "trimEnd": 900,
            "trimStart": 0,
            "updateTime": 0
        }
    },
    "/Volumes/LaCie/2026/March - Red Sea Egypt/61 Ocean Lovers Egypt - Marsa Shouna/media/IMG_20260326_121411_200.jpeg": {
        "default": {
            "totalFrames": 900,
            "trimEnd": 900,
            "trimStart": 0,
            "updateTime": 0
        }
    },
    "/Volumes/LaCie/2026/March - Red Sea Egypt/61 Ocean Lovers Egypt - Marsa Shouna/media/ScreenRecording_04-19-2026 16-04-38_1.MP4": {
        "default": {
            "totalFrames": 1245,
            "trimEnd": 1245,
            "trimStart": 0,
            "updateTime": 0
        }
    }
}
