{
    "/Volumes/LaCie/2026/January - Maldives/30 Felicity Maldives - South Male Atoll - Villivaru Giri/30 Felicity Maldives - South Male Atoll - Villivaru Giri/media/791506689.619088_109501769813899.MP4": {
        "default": {
            "totalFrames": 7715,
            "trimEnd": 7715,
            "trimStart": 0,
            "updateTime": 0
        }
    },
    "/Volumes/LaCie/2026/January - Maldives/30 Felicity Maldives - South Male Atoll - Villivaru Giri/30 Felicity Maldives - South Male Atoll - Villivaru Giri/media/791507123.720861_141021769814329.MP4": {
        "default": {
            "totalFrames": 3994,
            "trimEnd": 3994,
            "trimStart": 0,
            "updateTime": 0
        }
    },
    "/Volumes/LaCie/2026/January - Maldives/30 Felicity Maldives - South Male Atoll - Villivaru Giri/30 Felicity Maldives - South Male Atoll - Villivaru Giri/media/791507425.812115_204161769814631.MP4": {
        "default": {
            "totalFrames": 910,
            "trimEnd": 910,
            "trimStart": 0,
            "updateTime": 0
        }
    },
    "/Volumes/LaCie/2026/January - Maldives/30 Felicity Maldives - South Male Atoll - Villivaru Giri/30 Felicity Maldives - South Male Atoll - Villivaru Giri/media/791507498.82055_220061769814705.MP4": {
        "default": {
            "totalFrames": 2867,
            "trimEnd": 2867,
            "trimStart": 0,
            "updateTime": 0
        }
    },
    "/Volumes/LaCie/2026/January - Maldives/30 Felicity Maldives - South Male Atoll - Villivaru Giri/30 Felicity Maldives - South Male Atoll - Villivaru Giri/media/791507638.022153_251111769814842.MP4": {
        "default": {
            "totalFrames": 1679,
            "trimEnd": 1679,
            "trimStart": 0,
            "updateTime": 0
        }
    },
    "/Volumes/LaCie/2026/January - Maldives/30 Felicity Maldives - South Male Atoll - Villivaru Giri/30 Felicity Maldives - South Male Atoll - Villivaru Giri/media/791507875.314477_297361769815081.MP4": {
        "default": {
            "totalFrames": 1498,
            "trimEnd": 1498,
            "trimStart": 0,
            "updateTime": 0
        }
    },
    "/Volumes/LaCie/2026/January - Maldives/30 Felicity Maldives - South Male Atoll - Villivaru Giri/30 Felicity Maldives - South Male Atoll - Villivaru Giri/media/791507947.99141_313231769815152.MP4": {
        "default": {
            "totalFrames": 912,
            "trimEnd": 912,
            "trimStart": 0,
            "updateTime": 0
        }
    },
    "/Volumes/LaCie/2026/January - Maldives/30 Felicity Maldives - South Male Atoll - Villivaru Giri/30 Felicity Maldives - South Male Atoll - Villivaru Giri/media/791508240.364556_359481769815448.MP4": {
        "default": {
            "totalFrames": 1663,
            "trimEnd": 1663,
            "trimStart": 0,
            "updateTime": 0
        }
    },
    "/Volumes/LaCie/2026/January - Maldives/30 Felicity Maldives - South Male Atoll - Villivaru Giri/30 Felicity Maldives - South Male Atoll - Villivaru Giri/media/791508387.101246_375771769815592.MP4": {
        "default": {
            "totalFrames": 4047,
            "trimEnd": 4047,
            "trimStart": 0,
            "updateTime": 0
        }
    },
    "/Volumes/LaCie/2026/January - Maldives/30 Felicity Maldives - South Male Atoll - Villivaru Giri/30 Felicity Maldives - South Male Atoll - Villivaru Giri/media/791692389.225739_47041769999594.MP4": {
        "default": {
            "totalFrames": 5080,
            "trimEnd": 5080,
            "trimStart": 0,
            "updateTime": 0
        }
    },
    "/Volumes/LaCie/2026/January - Maldives/30 Felicity Maldives - South Male Atoll - Villivaru Giri/30 Felicity Maldives - South Male Atoll - Villivaru Giri/media/791692613.570585_77991769999820.MP4": {
        "default": {
            "totalFrames": 4543,
            "trimEnd": 4543,
            "trimStart": 0,
            "updateTime": 0
        }
    },
    "/Volumes/LaCie/2026/January - Maldives/30 Felicity Maldives - South Male Atoll - Villivaru Giri/30 Felicity Maldives - South Male Atoll - Villivaru Giri/media/791692798.354663_93781770000006.MP4": {
        "default": {
            "totalFrames": 860,
            "trimEnd": 860,
            "trimStart": 0,
            "updateTime": 0
        }
    },
    "/Volumes/LaCie/2026/January - Maldives/30 Felicity Maldives - South Male Atoll - Villivaru Giri/30 Felicity Maldives - South Male Atoll - Villivaru Giri/media/791734398.089863_32271770041603.MP4": {
        "default": {
            "totalFrames": 5662,
            "trimEnd": 5662,
            "trimStart": 0,
            "updateTime": 0
        }
    },
    "/Volumes/LaCie/2026/January - Maldives/30 Felicity Maldives - South Male Atoll - Villivaru Giri/30 Felicity Maldives - South Male Atoll - Villivaru Giri/media/791734627.08068_93421770041833.MP4": {
        "default": {
            "totalFrames": 4523,
            "trimEnd": 4523,
            "trimStart": 0,
            "updateTime": 0
        }
    },
    "/Volumes/LaCie/2026/January - Maldives/30 Felicity Maldives - South Male Atoll - Villivaru Giri/30 Felicity Maldives - South Male Atoll - Villivaru Giri/media/791734834.938321_169881770042039.MP4": {
        "default": {
            "totalFrames": 1815,
            "trimEnd": 1815,
            "trimStart": 0,
            "updateTime": 0
        }
    },
    "/Volumes/LaCie/2026/January - Maldives/30 Felicity Maldives - South Male Atoll - Villivaru Giri/30 Felicity Maldives - South Male Atoll - Villivaru Giri/media/791734936.263904_185841770042142.MP4": {
        "default": {
            "totalFrames": 2218,
            "trimEnd": 2218,
            "trimStart": 0,
            "updateTime": 0
        }
    },
    "/Volumes/LaCie/2026/January - Maldives/30 Felicity Maldives - South Male Atoll - Villivaru Giri/30 Felicity Maldives - South Male Atoll - Villivaru Giri/media/791735076.207003_201581770042280.MP4": {
        "default": {
            "totalFrames": 3463,
            "trimEnd": 3463,
            "trimStart": 0,
            "updateTime": 0
        }
    },
    "/Volumes/LaCie/2026/January - Maldives/30 Felicity Maldives - South Male Atoll - Villivaru Giri/30 Felicity Maldives - South Male Atoll - Villivaru Giri/media/IMG_0611.jpg": {
        "default": {
            "totalFrames": 900,
            "trimEnd": 900,
            "trimStart": 0,
            "updateTime": 0
        }
    },
    "/Volumes/LaCie/2026/January - Maldives/30 Felicity Maldives - South Male Atoll - Villivaru Giri/30 Felicity Maldives - South Male Atoll - Villivaru Giri/media/IMG_0612 copy.jpg": {
        "default": {
            "totalFrames": 900,
            "trimEnd": 900,
            "trimStart": 0,
            "updateTime": 0
        }
    },
    "/Volumes/LaCie/2026/January - Maldives/30 Felicity Maldives - South Male Atoll - Villivaru Giri/30 Felicity Maldives - South Male Atoll - Villivaru Giri/media/IMG_0613 copy.jpg": {
        "default": {
            "totalFrames": 900,
            "trimEnd": 900,
            "trimStart": 0,
            "updateTime": 0
        }
    },
    "/Volumes/LaCie/2026/January - Maldives/30 Felicity Maldives - South Male Atoll - Villivaru Giri/30 Felicity Maldives - South Male Atoll - Villivaru Giri/media/IMG_0614 copy.jpg": {
        "default": {
            "totalFrames": 900,
            "trimEnd": 900,
            "trimStart": 0,
            "updateTime": 0
        }
    },
    "/Volumes/LaCie/2026/January - Maldives/30 Felicity Maldives - South Male Atoll - Villivaru Giri/30 Felicity Maldives - South Male Atoll - Villivaru Giri/media/IMG_0615 copy.jpg": {
        "default": {
            "totalFrames": 900,
            "trimEnd": 900,
            "trimStart": 0,
            "updateTime": 0
        }
    },
    "/Volumes/LaCie/2026/January - Maldives/30 Felicity Maldives - South Male Atoll - Villivaru Giri/30 Felicity Maldives - South Male Atoll - Villivaru Giri/media/IMG_0669.MOV": {
        "default": {
            "totalFrames": 297,
            "trimEnd": 297,
            "trimStart": 0,
            "updateTime": 0
        }
    },
    "/Volumes/LaCie/2026/January - Maldives/30 Felicity Maldives - South Male Atoll - Villivaru Giri/30 Felicity Maldives - South Male Atoll - Villivaru Giri/media/ScreenRecording_02-07-2026 01-36-14_1.MP4": {
        "default": {
            "totalFrames": 1655,
            "trimEnd": 1655,
            "trimStart": 0,
            "updateTime": 0
        }
    }
}
